lab1/collatz.sv
module collatz( input logic         clk,   // Clock
		input logic 	    go,    // Load value from n; start iterating
		input logic  [31:0] n,     // Start value; only read when go = 1
		output logic [31:0] dout,  // Iteration value: true after go = 1
		output logic 	    done); // True when dout reaches 1

   /* Replace this comment and the code below with your solution */

    always_ff @(posedge clk) begin
        if (go) begin
            // Restart from n
            dout <= n;

            // Stop if n is already 1, otherwise start iterating
            done <= (n == 32'd1);
        end

        else if (!done) begin
            // Only advance if not finished
            logic [31:0] next;

            //Check even or odd
            if (dout[0] == 1'b0)
                next = dout >> 1;              // even: n/2
            else
                next = (dout * 32'd3) + 32'd1; // odd: 3n + 1

            // Update dout and done
            dout <= next;
            done <= (next == 32'd1);
        end
        // else: done stays asserted and dout holds its value (should be 1)
    end

   /* make collatz.vcd (based on tb) */
   /* Pass (7 22 11 34 17 52 26 13 40 20 10 5 16 8 4 2 1 for n = 7) */

endmodule

lab1/range.sv
module range
   #(parameter
     RAM_WORDS = 16,            // Number of counts to store in RAM
     RAM_ADDR_BITS = 4)         // Number of RAM address bits
   (input logic         clk,    // Clock
    input logic 	go,     // Read start and start testing
    input logic [31:0] 	start,  // Number to start from or count to read
    output logic 	done,   // True once memory is filled
    output logic [15:0] count); // Iteration count once finished

   logic 		cgo;    // go for the Collatz iterator
   logic                cdone;  // done from the Collatz iterator
   logic [31:0] 	n;      // number to start the Collatz iterator

// verilator lint_off PINCONNECTEMPTY
   
   // Instantiate the Collatz iterator
   collatz c1(.clk(clk),
	      .go(cgo),
	      .n(n),
	      .done(cdone),
	      .dout());

   logic [RAM_ADDR_BITS - 1:0] 	 num;         // The RAM address to write
   logic 			 running = 0; // True during the iterations

   /* Replace this comment and the code below with your solution,
      which should generate running, done, cgo, n, num, we, and din */
   
   // Extra stuff
   logic start_next = 1'b0;  // to start the next cycle
   logic wrote      = 1'b0;  // prevents repeated writes while cdone stays high
   logic [31:0] n_reg;

   // The last address we will write to (one less than the number of words), not sure about it
   localparam logic [RAM_ADDR_BITS-1:0] LAST_ADDR = RAM_ADDR_BITS'(RAM_WORDS - 1);

   // Start a new full sweep only when idle
   logic start_now;
   assign start_now = go && !running;

   // Pulse Collatz for one cycle at the start, and once per subsequent value
   assign cgo = start_now || start_next;

   // Make sure Collatz sees the correct n on the same edge
   assign n   = start_now ? start : n_reg;

   // go high for one cycle when cdone first appears
   assign we  = running && cdone && !wrote;

   always_ff @(posedge clk) begin
      // done is a pulse
      done <= 1'b0;

      // Start the first Collatz run when we see the go signal, and set up for subsequent runs
      if (start_now) begin
         running    <= 1'b1;
         n_reg      <= start;
         num        <= '0;
         din        <= 16'd1;
         wrote      <= 1'b0;
         start_next <= 1'b0;

      // During a run, we want to write the count when cdone goes high, 
      // and then set up the next run on the following cycle
      end else if (running) begin

         // Clear the cycle restart pulse after it has been used
         if (start_next) begin
            start_next <= 1'b0;
            wrote      <= 1'b0; // ready to detect the next completion
         end

         if (we) begin
            // A write will occur on this clock edge
            wrote <= 1'b1;

            // If we've just written to the last address, we're done. 
            // Otherwise, set up for the next Collatz run.
            if (num == LAST_ADDR) begin
               running <= 1'b0;
               done    <= 1'b1; // pulse done once RAM is filled
            end else begin
               num        <= num + 1'b1;
               n_reg      <= n_reg + 32'd1;
               din        <= 16'd1;
               start_next <= 1'b1; // start next Collatz run in the next cycle
            end

         // Ifnot writing, but Collatz just finished, set up for the next run
         end else if (!cdone && !start_next) begin
            // Count how many terms we've seen (starts at 1)
            din <= din + 16'd1;
         end
      end
   end

   /* Replace this comment and the code above with your solution */

   logic 			 we;                    // Write din to addr
   logic [15:0] 		 din;                   // Data to write
   logic [15:0] 		 mem[RAM_WORDS - 1:0];  // The RAM itself
   logic [RAM_ADDR_BITS - 1:0] 	 addr;                  // Address to read/write

   assign addr = we ? num : start[RAM_ADDR_BITS-1:0];
   
   always_ff @(posedge clk) begin
      if (we) mem[addr] <= din;
      count <= mem[addr];      
   end

endmodule

lab1/range.vcd
$version Generated by VerilatedVcd $end
$date Wed Feb 11 13:59:52 2026
 $end
$timescale   1ns $end

 $scope module TOP $end
  $var wire  1 W" clk $end
  $var wire 16 w" count [15:0] $end
  $var wire  1 o" done $end
  $var wire  1 _" go $end
  $var wire 32 g" start [31:0] $end
  $scope module range $end
   $var wire  4 1# LAST_ADDR [3:0] $end
   $var wire 32 )# RAM_ADDR_BITS [31:0] $end
   $var wire 32 !# RAM_WORDS [31:0] $end
   $var wire  4 [ addr [3:0] $end
   $var wire  1 c cdone $end
   $var wire  1 C cgo $end
   $var wire  1 W" clk $end
   $var wire 16 w" count [15:0] $end
   $var wire 16 { din [15:0] $end
   $var wire  1 o" done $end
   $var wire  1 _" go $end
   $var wire 16 %! mem(0) [15:0] $end
   $var wire 16 &! mem(1) [15:0] $end
   $var wire 16 /! mem(10) [15:0] $end
   $var wire 16 0! mem(11) [15:0] $end
   $var wire 16 1! mem(12) [15:0] $end
   $var wire 16 2! mem(13) [15:0] $end
   $var wire 16 3! mem(14) [15:0] $end
   $var wire 16 4! mem(15) [15:0] $end
   $var wire 16 '! mem(2) [15:0] $end
   $var wire 16 (! mem(3) [15:0] $end
   $var wire 16 )! mem(4) [15:0] $end
   $var wire 16 *! mem(5) [15:0] $end
   $var wire 16 +! mem(6) [15:0] $end
   $var wire 16 ,! mem(7) [15:0] $end
   $var wire 16 -! mem(8) [15:0] $end
   $var wire 16 .! mem(9) [15:0] $end
   $var wire 32 K n [31:0] $end
   $var wire 32 s n_reg [31:0] $end
   $var wire  4 k num [3:0] $end
   $var wire  1 # running $end
   $var wire 32 g" start [31:0] $end
   $var wire  1 + start_next $end
   $var wire  1 S start_now $end
   $var wire  1 ; we $end
   $var wire  1 3 wrote $end
   $scope module c1 $end
    $var wire  1 W" clk $end
    $var wire  1 c done $end
    $var wire 32 G" dout [31:0] $end
    $var wire  1 C go $end
    $var wire 32 K n [31:0] $end
    $scope module unnamedblk1 $end
     $var wire 32 O" next [31:0] $end
    $upscope $end
   $upscope $end
  $upscope $end
 $upscope $end
$enddefinitions $end


#0
0#
0+
03
0;
1C
b00000000000000000000000000000111 K
1S
b0111 [
0c
b0000 k
b00000000000000000000000000000000 s
b0000000000000000 {
b0000000000000000 %!
b0000000000000000 &!
b0000000000000000 '!
b0000000000000000 (!
b0000000000000000 )!
b0000000000000000 *!
b0000000000000000 +!
b0000000000000000 ,!
b0000000000000000 -!
b0000000000000000 .!
b0000000000000000 /!
b0000000000000000 0!
b0000000000000000 1!
b0000000000000000 2!
b0000000000000000 3!
b0000000000000000 4!
b00000000000000000000000000000000 G"
b00000000000000000000000000000000 O"
0W"
1_"
b00000000000000000000000000000111 g"
0o"
b0000000000000000 w"
b00000000000000000000000000010000 !#
b00000000000000000000000000000100 )#
b1111 1#
#10
1#
0C
0S
b00000000000000000000000000000111 s
b0000000000000001 {
b00000000000000000000000000000111 G"
1W"
#20
0W"
#30
b0000000000000010 {
b00000000000000000000000000010110 G"
b00000000000000000000000000010110 O"
1W"
#40
0W"
0_"
#50
b0000000000000011 {
b00000000000000000000000000001011 G"
b00000000000000000000000000001011 O"
1W"
#60
0W"
#70
b0000000000000100 {
b00000000000000000000000000100010 G"
b00000000000000000000000000100010 O"
1W"
#80
0W"
#90
b0000000000000101 {
b00000000000000000000000000010001 G"
b00000000000000000000000000010001 O"
1W"
#100
0W"
#110
b0000000000000110 {
b00000000000000000000000000110100 G"
b00000000000000000000000000110100 O"
1W"
#120
0W"
#130
b0000000000000111 {
b00000000000000000000000000011010 G"
b00000000000000000000000000011010 O"
1W"
#140
0W"
#150
b0000000000001000 {
b00000000000000000000000000001101 G"
b00000000000000000000000000001101 O"
1W"
#160
0W"
#170
b0000000000001001 {
b00000000000000000000000000101000 G"
b00000000000000000000000000101000 O"
1W"
#180
0W"
#190
b0000000000001010 {
b00000000000000000000000000010100 G"
b00000000000000000000000000010100 O"
1W"
#200
0W"
#210
b0000000000001011 {
b00000000000000000000000000001010 G"
b00000000000000000000000000001010 O"
1W"
#220
0W"
#230
b0000000000001100 {
b00000000000000000000000000000101 G"
b00000000000000000000000000000101 O"
1W"
#240
0W"
#250
b0000000000001101 {
b00000000000000000000000000010000 G"
b00000000000000000000000000010000 O"
1W"
#260
0W"
#270
b0000000000001110 {
b00000000000000000000000000001000 G"
b00000000000000000000000000001000 O"
1W"
#280
0W"
#290
b0000000000001111 {
b00000000000000000000000000000100 G"
b00000000000000000000000000000100 O"
1W"
#300
0W"
#310
b0000000000010000 {
b00000000000000000000000000000010 G"
b00000000000000000000000000000010 O"
1W"
#320
0W"
#330
1;
b0000 [
1c
b0000000000010001 {
b00000000000000000000000000000001 G"
b00000000000000000000000000000001 O"
1W"
#340
0W"
#350
1+
13
0;
1C
b00000000000000000000000000001000 K
b0111 [
b0001 k
b00000000000000000000000000001000 s
b0000000000000001 {
b0000000000010001 %!
1W"
#360
0W"
#370
0+
03
0C
0c
b00000000000000000000000000001000 G"
1W"
#380
0W"
#390
b0000000000000010 {
b00000000000000000000000000000100 G"
b00000000000000000000000000000100 O"
1W"
#400
0W"
#410
b0000000000000011 {
b00000000000000000000000000000010 G"
b00000000000000000000000000000010 O"
1W"
#420
0W"
#430
1;
b0001 [
1c
b0000000000000100 {
b00000000000000000000000000000001 G"
b00000000000000000000000000000001 O"
1W"
#440
0W"
#450
1+
13
0;
1C
b00000000000000000000000000001001 K
b0111 [
b0010 k
b00000000000000000000000000001001 s
b0000000000000001 {
b0000000000000100 &!
1W"
#460
0W"
#470
0+
03
0C
0c
b00000000000000000000000000001001 G"
1W"
#480
0W"
#490
b0000000000000010 {
b00000000000000000000000000011100 G"
b00000000000000000000000000011100 O"
1W"
#500
0W"
#510
b0000000000000011 {
b00000000000000000000000000001110 G"
b00000000000000000000000000001110 O"
1W"
#520
0W"
#530
b0000000000000100 {
b00000000000000000000000000000111 G"
b00000000000000000000000000000111 O"
1W"
#540
0W"
#550
b0000000000000101 {
b00000000000000000000000000010110 G"
b00000000000000000000000000010110 O"
1W"
#560
0W"
#570
b0000000000000110 {
b00000000000000000000000000001011 G"
b00000000000000000000000000001011 O"
1W"
#580
0W"
#590
b0000000000000111 {
b00000000000000000000000000100010 G"
b00000000000000000000000000100010 O"
1W"
#600
0W"
#610
b0000000000001000 {
b00000000000000000000000000010001 G"
b00000000000000000000000000010001 O"
1W"
#620
0W"
#630
b0000000000001001 {
b00000000000000000000000000110100 G"
b00000000000000000000000000110100 O"
1W"
#640
0W"
#650
b0000000000001010 {
b00000000000000000000000000011010 G"
b00000000000000000000000000011010 O"
1W"
#660
0W"
#670
b0000000000001011 {
b00000000000000000000000000001101 G"
b00000000000000000000000000001101 O"
1W"
#680
0W"
#690
b0000000000001100 {
b00000000000000000000000000101000 G"
b00000000000000000000000000101000 O"
1W"
#700
0W"
#710
b0000000000001101 {
b00000000000000000000000000010100 G"
b00000000000000000000000000010100 O"
1W"
#720
0W"
#730
b0000000000001110 {
b00000000000000000000000000001010 G"
b00000000000000000000000000001010 O"
1W"
#740
0W"
#750
b0000000000001111 {
b00000000000000000000000000000101 G"
b00000000000000000000000000000101 O"
1W"
#760
0W"
#770
b0000000000010000 {
b00000000000000000000000000010000 G"
b00000000000000000000000000010000 O"
1W"
#780
0W"
#790
b0000000000010001 {
b00000000000000000000000000001000 G"
b00000000000000000000000000001000 O"
1W"
#800
0W"
#810
b0000000000010010 {
b00000000000000000000000000000100 G"
b00000000000000000000000000000100 O"
1W"
#820
0W"
#830
b0000000000010011 {
b00000000000000000000000000000010 G"
b00000000000000000000000000000010 O"
1W"
#840
0W"
#850
1;
b0010 [
1c
b0000000000010100 {
b00000000000000000000000000000001 G"
b00000000000000000000000000000001 O"
1W"
#860
0W"
#870
1+
13
0;
1C
b00000000000000000000000000001010 K
b0111 [
b0011 k
b00000000000000000000000000001010 s
b0000000000000001 {
b0000000000010100 '!
1W"
#880
0W"
#890
0+
03
0C
0c
b00000000000000000000000000001010 G"
1W"
#900
0W"
#910
b0000000000000010 {
b00000000000000000000000000000101 G"
b00000000000000000000000000000101 O"
1W"
#920
0W"
#930
b0000000000000011 {
b00000000000000000000000000010000 G"
b00000000000000000000000000010000 O"
1W"
#940
0W"
#950
b0000000000000100 {
b00000000000000000000000000001000 G"
b00000000000000000000000000001000 O"
1W"
#960
0W"
#970
b0000000000000101 {
b00000000000000000000000000000100 G"
b00000000000000000000000000000100 O"
1W"
#980
0W"
#990
b0000000000000110 {
b00000000000000000000000000000010 G"
b00000000000000000000000000000010 O"
1W"
#1000
0W"
#1010
1;
b0011 [
1c
b0000000000000111 {
b00000000000000000000000000000001 G"
b00000000000000000000000000000001 O"
1W"
#1020
0W"
#1030
1+
13
0;
1C
b00000000000000000000000000001011 K
b0111 [
b0100 k
b00000000000000000000000000001011 s
b0000000000000001 {
b0000000000000111 (!
1W"
#1040
0W"
#1050
0+
03
0C
0c
b00000000000000000000000000001011 G"
1W"
#1060
0W"
#1070
b0000000000000010 {
b00000000000000000000000000100010 G"
b00000000000000000000000000100010 O"
1W"
#1080
0W"
#1090
b0000000000000011 {
b00000000000000000000000000010001 G"
b00000000000000000000000000010001 O"
1W"
#1100
0W"
#1110
b0000000000000100 {
b00000000000000000000000000110100 G"
b00000000000000000000000000110100 O"
1W"
#1120
0W"
#1130
b0000000000000101 {
b00000000000000000000000000011010 G"
b00000000000000000000000000011010 O"
1W"
#1140
0W"
#1150
b0000000000000110 {
b00000000000000000000000000001101 G"
b00000000000000000000000000001101 O"
1W"
#1160
0W"
#1170
b0000000000000111 {
b00000000000000000000000000101000 G"
b00000000000000000000000000101000 O"
1W"
#1180
0W"
#1190
b0000000000001000 {
b00000000000000000000000000010100 G"
b00000000000000000000000000010100 O"
1W"
#1200
0W"
#1210
b0000000000001001 {
b00000000000000000000000000001010 G"
b00000000000000000000000000001010 O"
1W"
#1220
0W"
#1230
b0000000000001010 {
b00000000000000000000000000000101 G"
b00000000000000000000000000000101 O"
1W"
#1240
0W"
#1250
b0000000000001011 {
b00000000000000000000000000010000 G"
b00000000000000000000000000010000 O"
1W"
#1260
0W"
#1270
b0000000000001100 {
b00000000000000000000000000001000 G"
b00000000000000000000000000001000 O"
1W"
#1280
0W"
#1290
b0000000000001101 {
b00000000000000000000000000000100 G"
b00000000000000000000000000000100 O"
1W"
#1300
0W"
#1310
b0000000000001110 {
b00000000000000000000000000000010 G"
b00000000000000000000000000000010 O"
1W"
#1320
0W"
#1330
1;
b0100 [
1c
b0000000000001111 {
b00000000000000000000000000000001 G"
b00000000000000000000000000000001 O"
1W"
#1340
0W"
#1350
1+
13
0;
1C
b00000000000000000000000000001100 K
b0111 [
b0101 k
b00000000000000000000000000001100 s
b0000000000000001 {
b0000000000001111 )!
1W"
#1360
0W"
#1370
0+
03
0C
0c
b00000000000000000000000000001100 G"
1W"
#1380
0W"
#1390
b0000000000000010 {
b00000000000000000000000000000110 G"
b00000000000000000000000000000110 O"
1W"
#1400
0W"
#1410
b0000000000000011 {
b00000000000000000000000000000011 G"
b00000000000000000000000000000011 O"
1W"
#1420
0W"
#1430
b0000000000000100 {
b00000000000000000000000000001010 G"
b00000000000000000000000000001010 O"
1W"
#1440
0W"
#1450
b0000000000000101 {
b00000000000000000000000000000101 G"
b00000000000000000000000000000101 O"
1W"
#1460
0W"
#1470
b0000000000000110 {
b00000000000000000000000000010000 G"
b00000000000000000000000000010000 O"
1W"
#1480
0W"
#1490
b0000000000000111 {
b00000000000000000000000000001000 G"
b00000000000000000000000000001000 O"
1W"
#1500
0W"
#1510
b0000000000001000 {
b00000000000000000000000000000100 G"
b00000000000000000000000000000100 O"
1W"
#1520
0W"
#1530
b0000000000001001 {
b00000000000000000000000000000010 G"
b00000000000000000000000000000010 O"
1W"
#1540
0W"
#1550
1;
b0101 [
1c
b0000000000001010 {
b00000000000000000000000000000001 G"
b00000000000000000000000000000001 O"
1W"
#1560
0W"
#1570
1+
13
0;
1C
b00000000000000000000000000001101 K
b0111 [
b0110 k
b00000000000000000000000000001101 s
b0000000000000001 {
b0000000000001010 *!
1W"
#1580
0W"
#1590
0+
03
0C
0c
b00000000000000000000000000001101 G"
1W"
#1600
0W"
#1610
b0000000000000010 {
b00000000000000000000000000101000 G"
b00000000000000000000000000101000 O"
1W"
#1620
0W"
#1630
b0000000000000011 {
b00000000000000000000000000010100 G"
b00000000000000000000000000010100 O"
1W"
#1640
0W"
#1650
b0000000000000100 {
b00000000000000000000000000001010 G"
b00000000000000000000000000001010 O"
1W"
#1660
0W"
#1670
b0000000000000101 {
b00000000000000000000000000000101 G"
b00000000000000000000000000000101 O"
1W"
#1680
0W"
#1690
b0000000000000110 {
b00000000000000000000000000010000 G"
b00000000000000000000000000010000 O"
1W"
#1700
0W"
#1710
b0000000000000111 {
b00000000000000000000000000001000 G"
b00000000000000000000000000001000 O"
1W"
#1720
0W"
#1730
b0000000000001000 {
b00000000000000000000000000000100 G"
b00000000000000000000000000000100 O"
1W"
#1740
0W"
#1750
b0000000000001001 {
b00000000000000000000000000000010 G"
b00000000000000000000000000000010 O"
1W"
#1760
0W"
#1770
1;
b0110 [
1c
b0000000000001010 {
b00000000000000000000000000000001 G"
b00000000000000000000000000000001 O"
1W"
#1780
0W"
#1790
1+
13
0;
1C
b00000000000000000000000000001110 K
b0111 [
b0111 k
b00000000000000000000000000001110 s
b0000000000000001 {
b0000000000001010 +!
1W"
#1800
0W"
#1810
0+
03
0C
0c
b00000000000000000000000000001110 G"
1W"
#1820
0W"
#1830
b0000000000000010 {
b00000000000000000000000000000111 G"
b00000000000000000000000000000111 O"
1W"
#1840
0W"
#1850
b0000000000000011 {
b00000000000000000000000000010110 G"
b00000000000000000000000000010110 O"
1W"
#1860
0W"
#1870
b0000000000000100 {
b00000000000000000000000000001011 G"
b00000000000000000000000000001011 O"
1W"
#1880
0W"
#1890
b0000000000000101 {
b00000000000000000000000000100010 G"
b00000000000000000000000000100010 O"
1W"
#1900
0W"
#1910
b0000000000000110 {
b00000000000000000000000000010001 G"
b00000000000000000000000000010001 O"
1W"
#1920
0W"
#1930
b0000000000000111 {
b00000000000000000000000000110100 G"
b00000000000000000000000000110100 O"
1W"
#1940
0W"
#1950
b0000000000001000 {
b00000000000000000000000000011010 G"
b00000000000000000000000000011010 O"
1W"
#1960
0W"
#1970
b0000000000001001 {
b00000000000000000000000000001101 G"
b00000000000000000000000000001101 O"
1W"
#1980
0W"
#1990
b0000000000001010 {
b00000000000000000000000000101000 G"
b00000000000000000000000000101000 O"
1W"
#2000
0W"
#2010
b0000000000001011 {
b00000000000000000000000000010100 G"
b00000000000000000000000000010100 O"
1W"
#2020
0W"
#2030
b0000000000001100 {
b00000000000000000000000000001010 G"
b00000000000000000000000000001010 O"
1W"
#2040
0W"
#2050
b0000000000001101 {
b00000000000000000000000000000101 G"
b00000000000000000000000000000101 O"
1W"
#2060
0W"
#2070
b0000000000001110 {
b00000000000000000000000000010000 G"
b00000000000000000000000000010000 O"
1W"
#2080
0W"
#2090
b0000000000001111 {
b00000000000000000000000000001000 G"
b00000000000000000000000000001000 O"
1W"
#2100
0W"
#2110
b0000000000010000 {
b00000000000000000000000000000100 G"
b00000000000000000000000000000100 O"
1W"
#2120
0W"
#2130
b0000000000010001 {
b00000000000000000000000000000010 G"
b00000000000000000000000000000010 O"
1W"
#2140
0W"
#2150
1;
1c
b0000000000010010 {
b00000000000000000000000000000001 G"
b00000000000000000000000000000001 O"
1W"
#2160
0W"
#2170
1+
13
0;
1C
b00000000000000000000000000001111 K
b1000 k
b00000000000000000000000000001111 s
b0000000000000001 {
b0000000000010010 ,!
1W"
#2180
0W"
#2190
0+
03
0C
0c
b00000000000000000000000000001111 G"
1W"
b0000000000010010 w"
#2200
0W"
#2210
b0000000000000010 {
b00000000000000000000000000101110 G"
b00000000000000000000000000101110 O"
1W"
#2220
0W"
#2230
b0000000000000011 {
b00000000000000000000000000010111 G"
b00000000000000000000000000010111 O"
1W"
#2240
0W"
#2250
b0000000000000100 {
b00000000000000000000000001000110 G"
b00000000000000000000000001000110 O"
1W"
#2260
0W"
#2270
b0000000000000101 {
b00000000000000000000000000100011 G"
b00000000000000000000000000100011 O"
1W"
#2280
0W"
#2290
b0000000000000110 {
b00000000000000000000000001101010 G"
b00000000000000000000000001101010 O"
1W"
#2300
0W"
#2310
b0000000000000111 {
b00000000000000000000000000110101 G"
b00000000000000000000000000110101 O"
1W"
#2320
0W"
#2330
b0000000000001000 {
b00000000000000000000000010100000 G"
b00000000000000000000000010100000 O"
1W"
#2340
0W"
#2350
b0000000000001001 {
b00000000000000000000000001010000 G"
b00000000000000000000000001010000 O"
1W"
#2360
0W"
#2370
b0000000000001010 {
b00000000000000000000000000101000 G"
b00000000000000000000000000101000 O"
1W"
#2380
0W"
#2390
b0000000000001011 {
b00000000000000000000000000010100 G"
b00000000000000000000000000010100 O"
1W"
#2400
0W"
#2410
b0000000000001100 {
b00000000000000000000000000001010 G"
b00000000000000000000000000001010 O"
1W"
#2420
0W"
#2430
b0000000000001101 {
b00000000000000000000000000000101 G"
b00000000000000000000000000000101 O"
1W"
#2440
0W"
#2450
b0000000000001110 {
b00000000000000000000000000010000 G"
b00000000000000000000000000010000 O"
1W"
#2460
0W"
#2470
b0000000000001111 {
b00000000000000000000000000001000 G"
b00000000000000000000000000001000 O"
1W"
#2480
0W"
#2490
b0000000000010000 {
b00000000000000000000000000000100 G"
b00000000000000000000000000000100 O"
1W"
#2500
0W"
#2510
b0000000000010001 {
b00000000000000000000000000000010 G"
b00000000000000000000000000000010 O"
1W"
#2520
0W"
#2530
1;
b1000 [
1c
b0000000000010010 {
b00000000000000000000000000000001 G"
b00000000000000000000000000000001 O"
1W"
#2540
0W"
#2550
1+
13
0;
1C
b00000000000000000000000000010000 K
b0111 [
b1001 k
b00000000000000000000000000010000 s
b0000000000000001 {
b0000000000010010 -!
1W"
b0000000000000000 w"
#2560
0W"
#2570
0+
03
0C
0c
b00000000000000000000000000010000 G"
1W"
b0000000000010010 w"
#2580
0W"
#2590
b0000000000000010 {
b00000000000000000000000000001000 G"
b00000000000000000000000000001000 O"
1W"
#2600
0W"
#2610
b0000000000000011 {
b00000000000000000000000000000100 G"
b00000000000000000000000000000100 O"
1W"
#2620
0W"
#2630
b0000000000000100 {
b00000000000000000000000000000010 G"
b00000000000000000000000000000010 O"
1W"
#2640
0W"
#2650
1;
b1001 [
1c
b0000000000000101 {
b00000000000000000000000000000001 G"
b00000000000000000000000000000001 O"
1W"
#2660
0W"
#2670
1+
13
0;
1C
b00000000000000000000000000010001 K
b0111 [
b1010 k
b00000000000000000000000000010001 s
b0000000000000001 {
b0000000000000101 .!
1W"
b0000000000000000 w"
#2680
0W"
#2690
0+
03
0C
0c
b00000000000000000000000000010001 G"
1W"
b0000000000010010 w"
#2700
0W"
#2710
b0000000000000010 {
b00000000000000000000000000110100 G"
b00000000000000000000000000110100 O"
1W"
#2720
0W"
#2730
b0000000000000011 {
b00000000000000000000000000011010 G"
b00000000000000000000000000011010 O"
1W"
#2740
0W"
#2750
b0000000000000100 {
b00000000000000000000000000001101 G"
b00000000000000000000000000001101 O"
1W"
#2760
0W"
#2770
b0000000000000101 {
b00000000000000000000000000101000 G"
b00000000000000000000000000101000 O"
1W"
#2780
0W"
#2790
b0000000000000110 {
b00000000000000000000000000010100 G"
b00000000000000000000000000010100 O"
1W"
#2800
0W"
#2810
b0000000000000111 {
b00000000000000000000000000001010 G"
b00000000000000000000000000001010 O"
1W"
#2820
0W"
#2830
b0000000000001000 {
b00000000000000000000000000000101 G"
b00000000000000000000000000000101 O"
1W"
#2840
0W"
#2850
b0000000000001001 {
b00000000000000000000000000010000 G"
b00000000000000000000000000010000 O"
1W"
#2860
0W"
#2870
b0000000000001010 {
b00000000000000000000000000001000 G"
b00000000000000000000000000001000 O"
1W"
#2880
0W"
#2890
b0000000000001011 {
b00000000000000000000000000000100 G"
b00000000000000000000000000000100 O"
1W"
#2900
0W"
#2910
b0000000000001100 {
b00000000000000000000000000000010 G"
b00000000000000000000000000000010 O"
1W"
#2920
0W"
#2930
1;
b1010 [
1c
b0000000000001101 {
b00000000000000000000000000000001 G"
b00000000000000000000000000000001 O"
1W"
#2940
0W"
#2950
1+
13
0;
1C
b00000000000000000000000000010010 K
b0111 [
b1011 k
b00000000000000000000000000010010 s
b0000000000000001 {
b0000000000001101 /!
1W"
b0000000000000000 w"
#2960
0W"
#2970
0+
03
0C
0c
b00000000000000000000000000010010 G"
1W"
b0000000000010010 w"
#2980
0W"
#2990
b0000000000000010 {
b00000000000000000000000000001001 G"
b00000000000000000000000000001001 O"
1W"
#3000
0W"
#3010
b0000000000000011 {
b00000000000000000000000000011100 G"
b00000000000000000000000000011100 O"
1W"
#3020
0W"
#3030
b0000000000000100 {
b00000000000000000000000000001110 G"
b00000000000000000000000000001110 O"
1W"
#3040
0W"
#3050
b0000000000000101 {
b00000000000000000000000000000111 G"
b00000000000000000000000000000111 O"
1W"
#3060
0W"
#3070
b0000000000000110 {
b00000000000000000000000000010110 G"
b00000000000000000000000000010110 O"
1W"
#3080
0W"
#3090
b0000000000000111 {
b00000000000000000000000000001011 G"
b00000000000000000000000000001011 O"
1W"
#3100
0W"
#3110
b0000000000001000 {
b00000000000000000000000000100010 G"
b00000000000000000000000000100010 O"
1W"
#3120
0W"
#3130
b0000000000001001 {
b00000000000000000000000000010001 G"
b00000000000000000000000000010001 O"
1W"
#3140
0W"
#3150
b0000000000001010 {
b00000000000000000000000000110100 G"
b00000000000000000000000000110100 O"
1W"
#3160
0W"
#3170
b0000000000001011 {
b00000000000000000000000000011010 G"
b00000000000000000000000000011010 O"
1W"
#3180
0W"
#3190
b0000000000001100 {
b00000000000000000000000000001101 G"
b00000000000000000000000000001101 O"
1W"
#3200
0W"
#3210
b0000000000001101 {
b00000000000000000000000000101000 G"
b00000000000000000000000000101000 O"
1W"
#3220
0W"
#3230
b0000000000001110 {
b00000000000000000000000000010100 G"
b00000000000000000000000000010100 O"
1W"
#3240
0W"
#3250
b0000000000001111 {
b00000000000000000000000000001010 G"
b00000000000000000000000000001010 O"
1W"
#3260
0W"
#3270
b0000000000010000 {
b00000000000000000000000000000101 G"
b00000000000000000000000000000101 O"
1W"
#3280
0W"
#3290
b0000000000010001 {
b00000000000000000000000000010000 G"
b00000000000000000000000000010000 O"
1W"
#3300
0W"
#3310
b0000000000010010 {
b00000000000000000000000000001000 G"
b00000000000000000000000000001000 O"
1W"
#3320
0W"
#3330
b0000000000010011 {
b00000000000000000000000000000100 G"
b00000000000000000000000000000100 O"
1W"
#3340
0W"
#3350
b0000000000010100 {
b00000000000000000000000000000010 G"
b00000000000000000000000000000010 O"
1W"
#3360
0W"
#3370
1;
b1011 [
1c
b0000000000010101 {
b00000000000000000000000000000001 G"
b00000000000000000000000000000001 O"
1W"
#3380
0W"
#3390
1+
13
0;
1C
b00000000000000000000000000010011 K
b0111 [
b1100 k
b00000000000000000000000000010011 s
b0000000000000001 {
b0000000000010101 0!
1W"
b0000000000000000 w"
#3400
0W"
#3410
0+
03
0C
0c
b00000000000000000000000000010011 G"
1W"
b0000000000010010 w"
#3420
0W"
#3430
b0000000000000010 {
b00000000000000000000000000111010 G"
b00000000000000000000000000111010 O"
1W"
#3440
0W"
#3450
b0000000000000011 {
b00000000000000000000000000011101 G"
b00000000000000000000000000011101 O"
1W"
#3460
0W"
#3470
b0000000000000100 {
b00000000000000000000000001011000 G"
b00000000000000000000000001011000 O"
1W"
#3480
0W"
#3490
b0000000000000101 {
b00000000000000000000000000101100 G"
b00000000000000000000000000101100 O"
1W"
#3500
0W"
#3510
b0000000000000110 {
b00000000000000000000000000010110 G"
b00000000000000000000000000010110 O"
1W"
#3520
0W"
#3530
b0000000000000111 {
b00000000000000000000000000001011 G"
b00000000000000000000000000001011 O"
1W"
#3540
0W"
#3550
b0000000000001000 {
b00000000000000000000000000100010 G"
b00000000000000000000000000100010 O"
1W"
#3560
0W"
#3570
b0000000000001001 {
b00000000000000000000000000010001 G"
b00000000000000000000000000010001 O"
1W"
#3580
0W"
#3590
b0000000000001010 {
b00000000000000000000000000110100 G"
b00000000000000000000000000110100 O"
1W"
#3600
0W"
#3610
b0000000000001011 {
b00000000000000000000000000011010 G"
b00000000000000000000000000011010 O"
1W"
#3620
0W"
#3630
b0000000000001100 {
b00000000000000000000000000001101 G"
b00000000000000000000000000001101 O"
1W"
#3640
0W"
#3650
b0000000000001101 {
b00000000000000000000000000101000 G"
b00000000000000000000000000101000 O"
1W"
#3660
0W"
#3670
b0000000000001110 {
b00000000000000000000000000010100 G"
b00000000000000000000000000010100 O"
1W"
#3680
0W"
#3690
b0000000000001111 {
b00000000000000000000000000001010 G"
b00000000000000000000000000001010 O"
1W"
#3700
0W"
#3710
b0000000000010000 {
b00000000000000000000000000000101 G"
b00000000000000000000000000000101 O"
1W"
#3720
0W"
#3730
b0000000000010001 {
b00000000000000000000000000010000 G"
b00000000000000000000000000010000 O"
1W"
#3740
0W"
#3750
b0000000000010010 {
b00000000000000000000000000001000 G"
b00000000000000000000000000001000 O"
1W"
#3760
0W"
#3770
b0000000000010011 {
b00000000000000000000000000000100 G"
b00000000000000000000000000000100 O"
1W"
#3780
0W"
#3790
b0000000000010100 {
b00000000000000000000000000000010 G"
b00000000000000000000000000000010 O"
1W"
#3800
0W"
#3810
1;
b1100 [
1c
b0000000000010101 {
b00000000000000000000000000000001 G"
b00000000000000000000000000000001 O"
1W"
#3820
0W"
#3830
1+
13
0;
1C
b00000000000000000000000000010100 K
b0111 [
b1101 k
b00000000000000000000000000010100 s
b0000000000000001 {
b0000000000010101 1!
1W"
b0000000000000000 w"
#3840
0W"
#3850
0+
03
0C
0c
b00000000000000000000000000010100 G"
1W"
b0000000000010010 w"
